rootlog/__init__.py
rootlog/config.py
rootlog_config-0.2.0.dist-info/LICENSE
rootlog_config-0.2.0.dist-info/METADATA
rootlog_config-0.2.0.dist-info/WHEEL
rootlog_config-0.2.0.dist-info/RECORD
