Metadata-Version: 2.3
Name: rootlog-config
Version: 0.2.0
Summary: Simple Python logging utility that configures the root logger properly. One function call for both console and file logging with colors, rotation, and thread safety.
License: MIT
Keywords: logging,logger,console,file,rotation,colors,thread-safe,root-logger
Author: Python Logger Contributors
Requires-Python: >=3.8,<4.0
Classifier: Development Status :: 4 - Beta
Classifier: Intended Audience :: Developers
Classifier: License :: OSI Approved :: MIT License
Classifier: Operating System :: OS Independent
Classifier: Programming Language :: Python :: 3
Classifier: Programming Language :: Python :: 3.8
Classifier: Programming Language :: Python :: 3.9
Classifier: Programming Language :: Python :: 3.10
Classifier: Programming Language :: Python :: 3.11
Classifier: Programming Language :: Python :: 3.12
Classifier: Programming Language :: Python :: 3.13
Classifier: Topic :: Software Development :: Libraries :: Python Modules
Classifier: Topic :: System :: Logging
Classifier: Topic :: Utilities
Requires-Dist: colorlog (>=6.9.0,<7.0.0)
Project-URL: Documentation, https://github.com/byte-pipe/simple-logger#readme
Project-URL: Homepage, https://github.com/byte-pipe/simple-logger
Project-URL: Repository, https://github.com/byte-pipe/simple-logger
